[
  {
    "id": 523523,
    "title": "Pete Tong, Ultra Naté, LP Giobbi, Jules Buckley - Free",
    "url": "https://www.youtube.com/watch?v=YrjOdt4816Q",
    "rating": 100
  },
  {
    "id": 523427,
    "title": "TCaptain & Tennille - Do That To Me One More Time",
    "url": "https://www.youtube.com/watch?v=z_XfJyrNLRQ",
    "rating": 230
  },
  {
    "id": 82653,
    "title": "Michelle Gurevich - First Six Months of Love",
    "url": "https://www.youtube.com/watch?v=NqGQIO2m3YQ",
    "rating": 2111
  },
  {
    "id": 858566,
    "title": "Stephen Sanchez - Until I Found You",
    "url": "https://www.youtube.com/watch?v=GxldQ9eX2wo",
    "rating": 11
  },
  {
    "id": 453538,
    "title": "Belle and Sebastian - Get Me Away from Here",
    "url": "https://www.youtube.com/watch?v=wcKsxHURj24",
    "rating": 3211
  },
  {
    "id": 283634,
    "title": "BILLIE EILISH AND FINNEAS - WHAT WAS I MADE FOR",
    "url": "https://www.youtube.com/watch?v=z8o75s-4fFY",
    "rating": 211
  },
  {
    "id": 562824,
    "title": "Ornella Vanoni - Arcobaleno",
    "url": "https://www.youtube.com/watch?v=Z9p-CecVK6Y",
    "rating": 111
  },
  {
    "id": 442452,
    "title": "Ornella Vanoni Perduto",
    "url": "https://www.youtube.com/watch?v=6Mj7mj4j27Y",
    "rating": 671
  },
  {
    "id": 536363,
    "title": "Jacob Collier - Little Blue",
    "url": "https://www.youtube.com/watch?v=Z2zLSkhANSY",
    "rating": 76
  },
  {
    "id": 323445,
    "title": "Papai Joci - Origo",
    "url": "https://www.youtube.com/watch?v=4ThtMlqyFqU",
    "rating": 73
  },
  {
    "id": 383645,
    "title": "Sade - Smooth Operator",
    "url": "https://www.youtube.com/watch?v=4TYv2PhG89A",
    "rating": 220
  }
]
